moovio_sdk/__init__.py
moovio_sdk/_hooks/__init__.py
moovio_sdk/_hooks/moov_version.py
moovio_sdk/_hooks/registration.py
moovio_sdk/_hooks/sdkhooks.py
moovio_sdk/_hooks/types.py
moovio_sdk/_version.py
moovio_sdk/account_terminal_applications.py
moovio_sdk/accounts.py
moovio_sdk/adjustments.py
moovio_sdk/apple_pay.py
moovio_sdk/authentication.py
moovio_sdk/avatars.py
moovio_sdk/bank_accounts.py
moovio_sdk/basesdk.py
moovio_sdk/branding.py
moovio_sdk/capabilities.py
moovio_sdk/card_issuing.py
moovio_sdk/cards.py
moovio_sdk/disputes.py
moovio_sdk/end_to_end_encryption.py
moovio_sdk/enriched_address.py
moovio_sdk/enriched_profile.py
moovio_sdk/fee_plans.py
moovio_sdk/files.py
moovio_sdk/httpclient.py
moovio_sdk/images.py
moovio_sdk/industries.py
moovio_sdk/institutions.py
moovio_sdk/invoices.py
moovio_sdk/issuing_transactions.py
moovio_sdk/models/__init__.py
moovio_sdk/models/components/__init__.py
moovio_sdk/models/components/account.py
moovio_sdk/models/components/accountcapability.py
moovio_sdk/models/components/accountcountries.py
moovio_sdk/models/components/accountfees.py
moovio_sdk/models/components/accountnameverification.py
moovio_sdk/models/components/accountterminalapplication.py
moovio_sdk/models/components/accounttype.py
moovio_sdk/models/components/accountverificationstatus.py
moovio_sdk/models/components/achcreditsamedaypaymentmethod.py
moovio_sdk/models/components/achcreditstandardpaymentmethod.py
moovio_sdk/models/components/achdebitcollectpaymentmethod.py
moovio_sdk/models/components/achdebitfundpaymentmethod.py
moovio_sdk/models/components/achexception.py
moovio_sdk/models/components/achfees.py
moovio_sdk/models/components/achinstitution.py
moovio_sdk/models/components/achlocation.py
moovio_sdk/models/components/achparticipant.py
moovio_sdk/models/components/achpaymentdetails.py
moovio_sdk/models/components/achpaymentdetailserror.py
moovio_sdk/models/components/achpaymentsettings.py
moovio_sdk/models/components/achreturncode.py
moovio_sdk-0.20.17.dist-info/METADATA
moovio_sdk-0.20.17.dist-info/WHEEL
moovio_sdk-0.20.17.dist-info/licenses/LICENSE
moovio_sdk-0.20.17.dist-info/RECORD
